autorouter/__init__.py
autorouter/client.py
autorouter/server.py
autorouter/test.py
autorouter/web_server.py
bots_autorouter/__init__.py
bots_autorouter/client.py
bots_autorouter/server.py
bots_autorouter/web_server.py
autorouter-0.0.6.dist-info/LICENSE
autorouter-0.0.6.dist-info/METADATA
autorouter-0.0.6.dist-info/WHEEL
autorouter-0.0.6.dist-info/top_level.txt
autorouter-0.0.6.dist-info/RECORD
