Metadata-Version: 2.1
Name: autorouter
Version: 0.0.6
Summary: small client-server url router
Home-page: https://github.com/svinerus/autorouter
Author: svinerus
Author-email: svinerus@gmail.com
License: UNKNOWN
Platform: UNKNOWN
Classifier: Programming Language :: Python :: 3
Classifier: License :: OSI Approved :: MIT License
Classifier: Operating System :: OS Independent
Requires-Python: >=3.6
Requires-Dist: websockets
